setup.py
gaegraph/__init__.py
gaegraph/business_base.py
gaegraph/model.py
gaegraph.egg-info/PKG-INFO
gaegraph.egg-info/SOURCES.txt
gaegraph.egg-info/dependency_links.txt
gaegraph.egg-info/not-zip-safe
gaegraph.egg-info/requires.txt
gaegraph.egg-info/top_level.txt